{"number":"02-106","rarity":"UC","setName":"やはり俺の青春ラブコメはまちがっている。続","name":"水族園デート","type":"イベント","usageCost":"0","outbreakCost":"2","color":"青","characteristic":[],"ap":"","dp":"","parallel":"○","text":"[メイン/自分]:メインエリアにいる『やはり俺の青春ラブコメはまちがっている。続』のキャラ1枚を指定する。その場合、デッキの上のカード5枚を見て、その中にある指定したキャラと同じ名称のキャラ1枚を抜き出し、表にしてから手札に加える。その後、デッキをシャッフルする。","flavor":"三人で見れて、良かった……。","image":"http://p-memories.com/images/product/ORG2/ORG2_02-106.jpg","url":"http://p-memories.com/node/747389","setAbbr":"ORG2","cost":"0","source":"2","num":"106","release":"02","id":"ORG2 02-106"}