{"number":"ST-010","rarity":"ST","setName":"グランベルム","name":"新月エルネスタ深海","type":"キャラクター","usageCost":"0","outbreakCost":"2","color":"青","characteristic":["制服\n魔術師"],"ap":"-","dp":"-","parallel":"","text":"このカードは、【制服】のコストとして使用する場合、発生コスト+2を得る。このカードが使用コストが7以上の自分のキャラがいる状態で登場した場合、カードを2枚引く。","flavor":"おそらく、それが最後の試練……マギアコナトスが最後に課した試練","image":"http://p-memories.com/images/product/GRAN/GRAN_ST-010.jpg","url":"http://p-memories.com/node/940108","setAbbr":"GRAN","cost":"0","source":"2","num":"010","release":"ST","id":"GRAN ST-010"}