{"number":"01-094","rarity":"SR（サイン）","setName":"AKB0048","name":"こじはる（8代目 小嶋陽菜）","type":"キャラクター","usageCost":"5","outbreakCost":"2","color":"赤","characteristic":"襲名メンバー、音楽","ap":"40","dp":"40","parallel":"","text":"〔天然2〕このカードがアプローチでポイントを与えた場合、自分の捨て札置き場にある『AKB0048』のキャラ1枚を休息状態で場に出すことができる。","flavor":"にゃんにゃん的にはぁ～、君達に足りないのはぁ～、フェロモンだと思うんだ！","image":"http://p-memories.com/images/product/AKB/AKB_01-094.jpg","url":"http://p-memories.com/node/313520","setAbbr":"AKB","num":"094","release":"01","id":"AKB_01-094"}