{"number":"01-024","rarity":"UC","setName":"アマガミSS+ plus","name":"七咲 逢","type":"キャラクター","usageCost":"3","outbreakCost":"2","color":"青","characteristic":["制服"],"ap":"0","dp":"50","parallel":"","text":"このカードが自分の捨て札置き場にある状態で、相手のアプローチによって自分のポイント置き場にカードが置かれた場合、手札1枚を捨て札にし、自分のポイント置き場にあるカード1枚を裏向きにすることで、このカードを場に出すことができる。","flavor":"わかりました、許してあげます。その代わり――","image":"http://p-memories.com/images/product/AMG/AMG_01-024.jpg","url":"http://p-memories.com/node/518304","setAbbr":"AMG","num":"024","release":"01","id":"AMG 01-024","cost":"3","source":"2"}