{"number":"01-126","rarity":"UC","setName":"アマガミSS+ plus","name":"まんま肉まん","type":"サポート","usageCost":"0","outbreakCost":"2","color":"黄","characteristic":"","ap":"","dp":"","parallel":"○","text":"このカードがセットされたキャラは、ターン終了時まで+20/+20を得る。［メイン/両方］:《0》このカードを捨て札にする。その場合、自分のキャラ1枚は、ターン終了時まで+20/+20を得る。","flavor":"まんま肉まん、ベリーおいしーネ。いっぱいいっぱいアイキャンイーットだよ～。","image":"http://p-memories.com/images/product/AMG/AMG_01-126.jpg","url":"http://p-memories.com/node/518406","setAbbr":"AMG","num":"126","release":"01","id":"AMG_01-126"}