{"number":"01-045","rarity":"R","setName":"恋愛ラボ","name":"榎本 結子","type":"キャラクター","usageCost":"4","outbreakCost":"2","color":"赤","characteristic":["-"],"ap":"30","dp":"30","parallel":"○","text":"このカードが登場した場合、デッキの上のカード5枚を見て、その中にある「榎本 結子」または「水嶋 沙依理」1枚と、『恋愛ラボ』のキャラ1枚を抜き出し、表にしてから手札に加える。その後、残りのカードを任意の順番でデッキの下に移す。","flavor":"『結子の髪は砂糖菓子みたいだね』って言われるためよっ！","image":"http://p-memories.com/images/product/LAB/LAB_01-045.jpg","url":"http://p-memories.com/node/555028","setAbbr":"LAB","num":"045","release":"01","id":"LAB 01-045","cost":"4","source":"2"}