{"number":"01-065","rarity":"SR","setName":"ハンドシェイカー","name":"三津寺 千鶴","type":"キャラクター","usageCost":"2","outbreakCost":"2","color":"青","characteristic":["和服"],"ap":"40","dp":"40","parallel":"","text":"このカードが登場した場合、相手のキャラ2枚は、このターン、「三津寺 千鶴」を妨害することができない。このカードが退場した場合、相手のキャラ1枚は、このターン、アプローチと妨害に参加することができない。","flavor":"だーかーらー。未成年じゃないってーの、もー。","image":"http://p-memories.com/images/product/HND/HND_01-065.jpg","url":"http://p-memories.com/node/875435","setAbbr":"HND","num":"065","release":"01","id":"HND 01-065","cost":"2","source":"2"}