{"number":"P-012","rarity":"P","setName":"俺の妹がこんなに可愛いわけがない。","name":"高坂 桐乃","type":"キャラクター","usageCost":"2","outbreakCost":"2","color":"黄","characteristic":"制服、オタク","ap":"30","dp":"30","parallel":"","text":"このカードが登場、または相手のアプローチによって自分のポイント置き場に置かれた場合、デッキの上のカード5枚を見て、その中にある「高坂 桐乃」1枚を抜き出し、表にしてから手札に加える。その後、残りのカードを任意の順番でデッキの下に移す。","flavor":"あたしを好きになってくれて……、ありがと……。","image":"http://p-memories.com/images/product/ORE2/ORE2_P-012.jpg","url":"http://p-memories.com/node/477599","setAbbr":"ORE2","num":"012","release":"P","id":"ORE2_P-012"}