{"number":"P-027","rarity":"P","setName":"NEW GAME!!","name":"大和・カトリーヌ・十和","type":"キャラクター","cost":"4","source":"0","color":"青","characteristic":["-"],"ap":"-","dp":"-","parallel":"","text":"〔EXカード〕それぞれ名称の異なる使用コストが4の自分のキャラが10枚以上いる場合、このカードは以下のテキストを得る。「相手のターンの終了時に、相手のポイント置き場にカードが4枚以上ある場合、自分はゲームに勝利する。」","flavor":"それだけでこのゲームは最高に近づく　できそうだろう？","image":"http://p-memories.com/images/product/NG2/NG2_P-027.jpg","url":"http://p-memories.com/node/959593","setAbbr":"NG2","num":"027","release":"P","id":"NG2 P-027"}