{"number":"02-028","rarity":"UC","setName":"ひだまりスケッチ","name":"二人でスケッチ","type":"イベント","usageCost":"0","outbreakCost":"2","color":"赤","characteristic":"","ap":"","dp":"","parallel":"","text":"[アプローチ/自分]:自分の〔コンビ〕を持つ『ひだまりスケッチ』のキャラ1枚は、ターン終了時まで+10/+10を得る。その場合、ターン終了時にそのキャラを活動状態にすることができる。","flavor":"ありがとう。もうちょっと仕上げちゃうね。","image":"http://p-memories.com/images/product/PM_HS/PM_HS_02-028.jpg","url":"http://p-memories.com/node/45221","setAbbr":"PM_HS","num":"028","release":"HS/PM_HS_02","id":"PM_HS/PM_HS_02-028"}