{"number":"04-052","rarity":"N","setName":"ガールズ＆パンツァー 最終章","name":"お銀","type":"キャラクター","usageCost":"4","outbreakCost":"2","color":"青","characteristic":["戦車道"],"ap":"50","dp":"50","parallel":"","text":"このカードがアプローチした場合、自分のキャラ1枚は、ターン終了時まで〔アクティブ〕を得る。そのキャラが「お銀」の場合、そのキャラは、ターン終了時まで+20/+20を得る。","flavor":"隊長は桃さんだよ。","image":"http://p-memories.com/images/product/GPFN/GPFN_04-052.jpg","url":"http://p-memories.com/node/932284","setAbbr":"GPFN","cost":"4","source":"2","num":"052","release":"04","id":"GPFN 04-052"}