{"number":"04-011","rarity":"R","setName":"ガールズ＆パンツァー 最終章","name":"武部 沙織","type":"キャラクター","usageCost":"4","outbreakCost":"2","color":"赤","characteristic":["制服\n戦車道"],"ap":"40","dp":"40","parallel":"","text":"このカードが登場した場合、自分の捨て札置き場にある「武部 沙織」2枚をデッキの下に移すことができる。移した場合、カードを2枚引く。このカードが退場した場合、自分の捨て札置き場にある〔支援〕を持つ【戦車道】1枚を場に出すことができる。","flavor":"河嶋先輩、学校にもう一年いるんだったら、広報はゆっくり引継ぎやりましょうよ。","image":"http://p-memories.com/images/product/GPFN/GPFN_04-011.jpg","url":"http://p-memories.com/node/932243","setAbbr":"GPFN","cost":"4","source":"2","num":"011","release":"04","id":"GPFN 04-011"}