{"number":"ST-057","rarity":"ST","setName":"魔法科高校の劣等生 来訪者編","name":"ムスペルスヘイム","type":"イベント","cost":"2","source":"2","color":"青","characteristic":[],"ap":"","dp":"","parallel":"","text":"《使用条件》:「アンジェリーナ=クドウ=シールズ」[メイン/自分]:使用コストが2以下の相手のキャラ1枚を捨て札にする。（《使用条件》:「アンジェリーナ=クドウ=シールズ」：このカードは、自分の「アンジェリーナ=クドウ=シールズ」がいる場合にのみプレイできる。）","flavor":"","image":"http://p-memories.com/images/product/MHK2/MHK2_ST-057.jpg","url":"http://p-memories.com/node/958797","setAbbr":"MHK2","num":"057","release":"ST","id":"MHK2 ST-057"}