{"number":"02-017","rarity":"R（サイン）","setName":"ゆるゆり♪♪","name":"船見 結衣","type":"キャラクター","usageCost":"3","outbreakCost":"2","color":"緑","characteristic":["制服","ごらく部"],"ap":"30","dp":"30","parallel":"","text":"このカードがアプローチまたは妨害に参加した場合、自分の捨て札置き場にある【ごらく部】を持つキャラを5枚まで任意の順番でデッキの下に移す。その場合、このカードは、デッキに移したキャラ1枚につき、ターン終了時まで±0/+10を得る。","flavor":"ち、ちなつちゃんの淹れたお茶、もっと飲みたいなあ～。","image":"http://p-memories.com/images/product/YRYR2/YRYR2_02-017.jpg","url":"http://p-memories.com/node/459727","setAbbr":"YRYR2","num":"017","release":"02","id":"YRYR2 02-017","cost":"3","source":"2"}