{"number":"02-023","rarity":"UC","setName":"ゆるゆり♪♪","name":"歳納 京子","type":"キャラクター","usageCost":"2","outbreakCost":"2","color":"青","characteristic":["水着","ごらく部","オタク"],"ap":"30","dp":"30","parallel":"○","text":"このカードが登場した場合、自分の全てのキャラは、ターン終了時まで+10/+10を得る。その場合、ターン終了時に自分の全てのキャラを活動状態にする。","flavor":"じゃあ私、スーパーセクシーコマンドー京子。","image":"http://p-memories.com/images/product/YRYR2/YRYR2_02-023.jpg","url":"http://p-memories.com/node/459733","setAbbr":"YRYR2","num":"023","release":"02","id":"YRYR2 02-023","cost":"2","source":"2"}