{"number":"02-010","rarity":"R","setName":"ハロー！！きんいろモザイク","name":"九条 カレン","type":"キャラクター","usageCost":"4","outbreakCost":"2","color":"緑","characteristic":"メイド、お嬢様","ap":"40","dp":"30","parallel":"○","text":"このカードは、自分の「九条 カレン」または【メイド】を持つキャラが登場した場合、ターン終了時まで+20/+20を得る。［メイン/自分］:《0》手札から【メイド】を持つキャラ2枚を捨て札にする。その場合、このカードは、このターン、妨害されない。","flavor":"いつもお菓子ありがとうゴジャイマス！","image":"http://p-memories.com/images/product/HKM/HKM_02-010.jpg","url":"http://p-memories.com/node/726901","setAbbr":"HKM","num":"010","release":"02","id":"HKM_02-010"}