{"number":"01-041","rarity":"SR(直筆サイン)","setName":"STEINS;GATE","name":"椎名 まゆり","type":"キャラクター","usageCost":"3","outbreakCost":"0","color":"緑","characteristic":["巫女服","コスプレ","オタク"],"ap":"50","dp":"40","parallel":"","text":"〔EXカード〕〔アクティブ〕このカードがアプローチした場合、このターン、自分の全ての「椎名 まゆり」は+20/+20を得る。相手のイベントカードがプレイされるごとに、自分の「椎名 まゆり」1枚を活動状態にすることができる。","flavor":"トゥットゥルー♪ まゆしぃでーす。","image":"http://p-memories.com/images/product/SG/SG_01-041.jpg","url":"http://p-memories.com/node/922541","setAbbr":"SG","cost":"3","source":"0","num":"041","release":"01","id":"SG 01-041"}