{"number":"01-024","rarity":"UC","setName":"ハイスクールＤ×Ｄ ＢｏｒＮ","name":"ロスヴァイセ","type":"キャラクター","usageCost":"2","outbreakCost":"2","color":"赤","characteristic":["オカルト研究部","水着"],"ap":"40","dp":"40","parallel":"","text":"このカードがアプローチに参加した場合、このターン、このターンの間に登場したキャラは、妨害に参加することができない。このカードが登場した場合、このターン、このターンの間に登場したキャラは、妨害に参加することができない。","flavor":"どうして私には恋人の一人もできないのかしら!?","image":"http://p-memories.com/images/product/DDB/DDB_01-024.jpg","url":"http://p-memories.com/node/803212","setAbbr":"DDB","cost":"2","source":"2","num":"024","release":"01","id":"DDB 01-024"}