{"number":"01-009","rarity":"R","setName":"カードキャプターさくら","name":"木之本 桜","type":"キャラクター","usageCost":"3","outbreakCost":"2","color":"赤","characteristic":["制服","カードキャプター","魔法少女"],"ap":"20","dp":"50","parallel":"○","text":"〔カードキャプター〕自分の「木之本 桜」のアプローチで相手のキャラが退場した場合、自分の捨て札置き場にある『カードキャプターさくら』のキャラを3枚まで任意の順番でデッキの下に移すことができる。","flavor":"あなた力……パワー 『力』のカードでしょ！　わ、わ、わたしと力比べしない!?","image":"http://p-memories.com/images/product/CCS/CCS_01-009.jpg","url":"http://p-memories.com/node/604145","setAbbr":"CCS","num":"009","release":"01","id":"CCS 01-009","cost":"3","source":"2"}