{"number":"02-004","rarity":"SR(箔押し)","setName":"劇場版「SHIROBAKO」","name":"宮森 あおい","type":"キャラクター","cost":"2","source":"3","color":"赤","characteristic":["武蔵野アニメーション\n制作進行\n水着"],"ap":"-","dp":"-","parallel":"","text":"このカードが登場した場合、手札にある「宮森 あおい」1枚を場に出すことができる。[メイン/相手]:《休》カードを1枚引く。その場合、このカードを捨て札にする。","flavor":"皆に良いアニメを作って貰えるよう、頑張りたいです！","image":"http://p-memories.com/images/product/SRBKM/SRBKM_02-004.jpg","url":"http://p-memories.com/node/944596","setAbbr":"SRBKM","num":"004","release":"02","id":"SRBKM 02-004"}