{"number":"ST-006","rarity":"ST","setName":"結城友奈は勇者である","name":"三好 夏凜","type":"キャラクター","usageCost":"3","outbreakCost":"2","color":"赤","characteristic":["勇者部　勇者"],"ap":"40","dp":"40","parallel":"","text":"〔レベルアップ〕〔アクティブ〕このカードが登場した場合、またはこのカードにレベルアップした場合、このカードは、ターン終了時まで退場しない。《LV3》このカードが妨害された場合、「三好 夏凜」1枚は、活動状態になるとともに、このターン、もう一度アプローチに参加することができる。","flavor":"言われなくても殲滅してやるわ。","image":"http://p-memories.com/images/product/YYY/YYY_ST-006.jpg","url":"http://p-memories.com/node/883355","setAbbr":"YYY","cost":"3","source":"2","num":"006","release":"ST","id":"YYY ST-006"}