{"number":"01-070","rarity":"R","setName":"まちカドまぞく","name":"陽夏木 ミカン","type":"キャラクター","usageCost":"0","outbreakCost":"2","color":"黄","characteristic":["制服\n魔法少女"],"ap":"-","dp":"-","parallel":"","text":"このカードが登場した場合、EXデッキから「陽夏木 ミカン」1枚を抜き出し、手札に移す。[メイン/相手]:《1》サポートエリアにいる相手のキャラ1枚を休息状態にする。その場合、このカードを捨て札にする。","flavor":"だから早く見つけてあげないと!!","image":"http://p-memories.com/images/product/MZK/MZK_01-070.jpg","url":"http://p-memories.com/node/942248","setAbbr":"MZK","cost":"0","source":"2","num":"070","release":"01","id":"MZK 01-070"}