{"number":"ST-001","rarity":"ST","setName":"SSSS.GRIDMAN","name":"響 裕太","type":"キャラクター","usageCost":"2","outbreakCost":"3","color":"赤","characteristic":["制服"],"ap":"40","dp":"40","parallel":"","text":"このカードが登場した場合、自分のポイント置き場にある『SSSS.GRIDMAN』のカード1枚を手札に加える。その場合、デッキの上のカード1枚を自分のポイント置き場に表向きで置く。","flavor":"オレの使命…？","image":"http://p-memories.com/images/product/SSSS/SSSS_ST-001.jpg","url":"http://p-memories.com/node/926903","setAbbr":"SSSS","cost":"2","source":"3","num":"001","release":"ST","id":"SSSS ST-001"}