{"number":"02-125","rarity":"UC","setName":"けいおん！Part2","name":"ティーセット","type":"サポート","usageCost":"0","outbreakCost":"1","color":"緑","characteristic":[],"ap":"","dp":"","parallel":"","text":"このカードがセットされている【お嬢様】を持つキャラは、±0/+10を得る。[メイン/両方]:《0》このカードがセットされているキャラは、ターン終了時まで±0/+20を得る。その場合、このカードを捨て札にする。","flavor":"","image":"http://p-memories.com/images/product/PM_K-ON_Part2/PM_K-ON_Part2_02-125.jpg","url":"http://p-memories.com/node/6200","setAbbr":"PM_K-ON_Part2","num":"125","release":"02","id":"PM_K-ON_Part2 02-125","cost":"0","source":"1"}