{"number":"01-102","rarity":"R","setName":"魔法使いの夜","name":"帰還","type":"イベント","usageCost":"2","outbreakCost":"2","color":"青","characteristic":"","ap":"","dp":"","parallel":"○","text":"[アプローチ/自分]:このターンの間に、アプローチに参加している自分のキャラ1枚を指定する。その場合、自分の捨て札置き場にあるキャラ2枚を手札に戻す。その場合、指定したキャラを活動状態にすることができる。","flavor":"橙子さんはどうなったの？……いや。よく分からないけど、橙子さんは帰ったよ。","image":"http://p-memories.com/images/product/WHN/WHN_01-102.jpg","url":"http://p-memories.com/node/426518","setAbbr":"WHN","num":"102","release":"01","id":"WHN_01-102"}