{"number":"01-112","rarity":"UC","setName":"魔法使いの夜","name":"圧倒的な魔弾の威力","type":"イベント","usageCost":"0","outbreakCost":"2","color":"赤","characteristic":[],"ap":"","dp":"","parallel":"","text":"[アプローチ/自分]:任意の枚数の手札を捨て札にする。その場合、アプローチに参加している【魔術師】を持つキャラ1枚は、捨て札にした手札1枚につき、ターン終了時まで+10/±0を得る。その場合、ターン終了時に捨て札にした手札と同じ枚数のカードを引く。","flavor":"両手にまとった魔弾の威力は、橙子の用意したルーンを壁ごとぶち抜いて余りある―――！","image":"http://p-memories.com/images/product/WHN/WHN_01-112.jpg","url":"http://p-memories.com/node/426528","setAbbr":"WHN","num":"112","release":"01","id":"WHN 01-112","cost":"0","source":"2"}