{"number":"01-062","rarity":"UC","setName":"とある科学の超電磁砲＆とある科学の超電磁砲Ｓ","name":"食蜂 操祈","type":"キャラクター","usageCost":"2","outbreakCost":"2","color":"青","characteristic":["制服","能力者"],"ap":"30","dp":"0","parallel":"","text":"このカードが登場した場合、相手のキャラ1枚は、このターン、妨害に参加することができず、テキストを使用することができない。このカードが登場した場合、このターン、相手の手札にある全てのイベントカードは、使用コスト+1を得る。","flavor":"私の改竄力でどうとでもなっちゃうものね～。","image":"http://p-memories.com/images/product/TKR/TKR_01-062.jpg","url":"http://p-memories.com/node/841788","setAbbr":"TKR","num":"062","release":"01","id":"TKR 01-062","cost":"2","source":"2"}