{"number":"05-007","rarity":"C","setName":"<物語>シリーズ","name":"戦場ヶ原 ひたぎ","type":"キャラクター","usageCost":"1","outbreakCost":"2","color":"赤","characteristic":["-"],"ap":"30","dp":"30","parallel":"○","text":"このカードが登場した場合、相手のデッキの上のカード1枚を表にする。その場合、相手は、そのカードを捨て札にすることができる。捨て札にした場合、全てのプレイヤーは、カードを1枚引く。","flavor":"手料理を食べて相手の人となりがわかるなんて、某料理漫画みたいだけどね。","image":"http://p-memories.com/images/product/MGS/MGS_05-007.jpg","url":"http://p-memories.com/node/719891","setAbbr":"MGS","num":"007","release":"05","id":"MGS 05-007","cost":"1","source":"2"}