{"number":"05-074","rarity":"C","setName":"<物語>シリーズ","name":"斧乃木 余接","type":"キャラクター","usageCost":"2","outbreakCost":"2","color":"緑","characteristic":["怪異"],"ap":"30","dp":"10","parallel":"","text":"このカードがアプローチに参加した場合、自分のキャラ1枚のAP/DPの値を、ターン終了時まで50/50に変更する。その場合、ターン終了時にそのキャラを活動状態にすることができる。","flavor":"低空は無理だね。低速なら出来るけど、そうする？","image":"http://p-memories.com/images/product/MGS/MGS_05-074.jpg","url":"http://p-memories.com/node/719958","setAbbr":"MGS","num":"074","release":"05","id":"MGS 05-074","cost":"2","source":"2"}