{"number":"01-012","rarity":"R","setName":"ささみさん＠がんばらない","name":"玉藻前","type":"キャラクター","usageCost":"1","outbreakCost":"2","color":"赤","characteristic":["和服"],"ap":"30","dp":"0","parallel":"○","text":"このカードが登場した場合、手札から「蝦怒川 情雨」または【和服】を持つキャラ1枚を休息状態で場に出すことができる。この効果で「蝦怒川 情雨」を場に出した場合、このカードと、そのキャラの上に+10/+10コインを1個乗せる。","flavor":"「おじょうさま」にとって他人は、敵か下僕の二つしか区別がないんですわ！","image":"http://p-memories.com/images/product/SAG/SAG_01-012.jpg","url":"http://p-memories.com/node/518429","setAbbr":"SAG","num":"012","release":"01","id":"SAG 01-012","cost":"1","source":"2"}