{"number":"01-050","rarity":"R","setName":"結城友奈は勇者である","name":"東郷 美森","type":"キャラクター","usageCost":"2","outbreakCost":"2","color":"青","characteristic":["勇者部　制服"],"ap":"30","dp":"30","parallel":"","text":"このカードが登場、または相手のアプローチによってポイント置き場に置かれた場合、デッキの上のカード5枚を見て、その中にある「東郷 美森」1枚を抜き出し、表にしてから手札に加える。その後、残りのカードを任意の順番でデッキの下に移す。","flavor":"私、いつも友奈ちゃんに護ってもらってた。","image":"http://p-memories.com/images/product/YYY/YYY_01-050.jpg","url":"http://p-memories.com/node/883270","setAbbr":"YYY","cost":"2","source":"2","num":"050","release":"01","id":"YYY 01-050"}