{"number":"P-043","rarity":"P","setName":"映画「けいおん！」","name":"秋山 澪&田井中 律","type":"キャラクター","usageCost":"2","outbreakCost":"2","color":"青","characteristic":"-","ap":"-","dp":"-","parallel":"","text":"〔コンビ〕［メイン/自分］:《休》自分の『けいおん！』のキャラ2枚は、ターン終了時まで+20/+20を得る。［アプローチ/両方］:《休》手札1枚を捨て札にする。その場合、自分の『けいおん！』のキャラを2枚まで活動状態にすることができる。","flavor":"昨日寝る前に新しい歌詞書いたんだけど。お、新曲？","image":"http://p-memories.com/images/product/KONM/KONM_P-043.jpg","url":"http://p-memories.com/node/796078","setAbbr":"KONM","num":"043","release":"P","id":"KONM_P-043"}