{"number":"ST-017","rarity":"ST","setName":"STEINS;GATE","name":"椎名 まゆり","type":"キャラクター","usageCost":"2","outbreakCost":"2","color":"緑","characteristic":["オタク"],"ap":"-","dp":"-","parallel":"","text":"[メイン/自分]:《休》自分の『STEINS;GATE』のキャラ1枚は、ターン終了時まで〔アクティブ〕を得るとともに、ターン終了時に活動状態になる。（〔アクティブ〕：このカードは、登場したターンでもアプローチできる。ただし、先攻の1ターン目はアプローチできない。）","flavor":"雷ネットソーセージも買わなきゃいけないし。","image":"http://p-memories.com/images/product/SG/SG_ST-017.jpg","url":"http://p-memories.com/node/922639","setAbbr":"SG","cost":"2","source":"2","num":"017","release":"ST","id":"SG ST-017"}